darkhorsesapi/__init__.py
darkhorsesapi/client.py
darkhorsesapi-1.0.1.dist-info/LICENSE
darkhorsesapi-1.0.1.dist-info/METADATA
darkhorsesapi-1.0.1.dist-info/WHEEL
darkhorsesapi-1.0.1.dist-info/top_level.txt
darkhorsesapi-1.0.1.dist-info/RECORD
