Metadata-Version: 2.1
Name: darkhorsesapi
Version: 1.0.1
Summary: An API client library for Dark Horses API.
Home-page: https://github.com/darkhorsestech/darkhorsesapi
Author: Craig Carmichael
Author-email: operations@darkhorsestech.com
License: MIT
License-File: LICENSE
Requires-Dist: requests
Requires-Dist: pandas
